kahnfigh/__init__.py
kahnfigh/core.py
kahnfigh/utils.py
kahnfigh-0.0.3.dist-info/LICENSE
kahnfigh-0.0.3.dist-info/METADATA
kahnfigh-0.0.3.dist-info/WHEEL
kahnfigh-0.0.3.dist-info/top_level.txt
kahnfigh-0.0.3.dist-info/RECORD
