Metadata-Version: 2.1
Name: kahnfigh
Version: 0.0.3
Summary: Boosted dictionaries to make complex and nested configuration files easier
Home-page: https://github.com/mrpep/kahnfigh
Author: Leonardo Pepino
Author-email: leonardodpepino@gmail.com
License: UNKNOWN
Platform: UNKNOWN
Classifier: Programming Language :: Python :: 3
Classifier: Operating System :: OS Independent
Requires-Python: >=3.6
License-File: LICENSE
Requires-Dist: dpath
Requires-Dist: ruamel-yaml
Requires-Dist: numpy
